slackstyler/__init__.py
slackstyler/slackstyler.py
slackstyler-0.0.2.dist-info/LICENSE
slackstyler-0.0.2.dist-info/METADATA
slackstyler-0.0.2.dist-info/WHEEL
slackstyler-0.0.2.dist-info/RECORD
