Metadata-Version: 2.1
Name: slackstyler
Version: 0.0.2
Summary: slackstyler is a Python package that converts strings written in Markdown into Slack message formatting. It provides a simple and convenient conversion of Markdown styles into Slack styles and can be effectively used when creating or integrating with Slack bots.
License: MIT
Author: Youngwook Kim
Author-email: youngwook.kim@gmail.com
Requires-Python: >=3.8,<4.0
Classifier: License :: OSI Approved :: MIT License
Classifier: Programming Language :: Python :: 3
Classifier: Programming Language :: Python :: 3.8
Classifier: Programming Language :: Python :: 3.9
Classifier: Programming Language :: Python :: 3.10
Classifier: Programming Language :: Python :: 3.11
Requires-Dist: mistune (<1)
